{
    "configurations": [
        {
            "name": "Linux",
            "includePath": [
                "${workspaceFolder}/**",
                "/usr/include/glib-2.0",
                "/usr/lib/x86_64-linux-gnu/glib-2.0/include",
                "/usr/local/include/libvmaf"
            ],
            "defines": [],
            "compilerPath": "/usr/bin/clang-10",
            "cStandard": "c11",
            "cppStandard": "c++14",
            "intelliSenseMode": "linux-clang-x64"
        }
    ],
    "version": 4
}